{
  "post_id": 29,
  "comment_count": 7,
  "comments": [
    {
      "id": 403,
      "author": "Hameed Sumbal",
      "email": "hsumbal@hotmail.com",
      "date": "2005-03-13 16:49:04",
      "content": "\t<p>Hi,</p>\n\n\t<p>Imad; what a wonderful efort. You have addressed a very common problem faced by almost all the diesel converted vehicles, specially 4&#215;4s.</p>\n\n\t<p>The article was very very informative.</p>\n\n\t<p>Looking forward to more technical tips and articles from you.</p>\n\n\t<p>Keep it up.</p>\n\n\t<p>Hameed</p>\n\n\n ",
      "parent_id": 0,
      "approved": true
    },
    {
      "id": 404,
      "author": "Yaseen",
      "email": "yaseen@offroadpakistan.com",
      "date": "2005-05-08 13:06:27",
      "content": "\t<p>Imad,</p>\n\n\t<p>Good article Ims. One correction &#8211; You need to get rid of third paragraph as its a repitition of the first paragraph.</p>\n\n\n ",
      "parent_id": 0,
      "approved": true
    },
    {
      "id": 405,
      "author": "Imad",
      "email": "imad.ali@gmail.com",
      "date": "2005-05-18 13:18:22",
      "content": "\t<p>The first paragraph was actually supposed to be a leader for the main article with a &#8220;more&#8221; link appended to it. However, the website layout was revamped so it appears to be a repetition.</p>\n\n\n ",
      "parent_id": 0,
      "approved": true
    },
    {
      "id": 406,
      "author": "gene werner",
      "email": "docmek@aol.com",
      "date": "2005-12-01 13:24:49",
      "content": "\t<p>Thank you for your insight into the cooling system.It was very informative! I have a question maybe you can awnser.with a carbeurated engine no concerns  about pollution, just performance and long life what is The optimum temperature?I know some people will run 210 for a few horsepower!What would be the absolute coldest I could run an engine without  concerns about excessive engine wear?</p>\n\n\t<p>My particular engine is an aluminum Yamaha V4 1200cc water cooled with electric fan. I would give up horsepower for engine life and less oil breakdown!</p>\n\n\n ",
      "parent_id": 0,
      "approved": true
    },
    {
      "id": 407,
      "author": "Imad",
      "email": "lt1_madness@offroadpakistan.com",
      "date": "2005-12-03 23:22:46",
      "content": "\t<p>Gene,</p>\n\n\t<p>Please post your question in the forums. This discussion will help many others over there as well.</p>\n\n\t<p>~Imad</p>\n\n\n ",
      "parent_id": 0,
      "approved": true
    },
    {
      "id": 408,
      "author": "saif",
      "email": "msur@hotmail.com",
      "date": "2007-05-05 19:30:35",
      "content": "\t<p>hi</p>\n\n\t<p>great article. Can u suggest a good electric fan for radiator that is easily available in pakistan</p>\n\n\t<p>keep it up</p>\n\n\n ",
      "parent_id": 0,
      "approved": true
    },
    {
      "id": 1290,
      "author": "Imad Ali",
      "email": "imad.ali@gmail.com",
      "date": "2011-07-25 23:49:24",
      "content": "Needs editing pronto!",
      "parent_id": 0,
      "approved": true
    }
  ]
}